Instrument/Instrument.py
Instrument/__init__.py
Instrument/test.py
PyMusic_Instrument-0.5.dist-info/LICENSE
PyMusic_Instrument-0.5.dist-info/METADATA
PyMusic_Instrument-0.5.dist-info/WHEEL
PyMusic_Instrument-0.5.dist-info/top_level.txt
PyMusic_Instrument-0.5.dist-info/RECORD
