Metadata-Version: 2.1
Name: PyMusic-Instrument
Version: 0.5
Summary: A python library which can generate sounds played by instruments
Home-page: https://www.github.com/Ibrahim2750mi/PyMusic-Instrument
Author: Mohammad Ibrahim
Author-email: cshore.2750mi@gmail.com
License: MIT
Classifier: License :: OSI Approved :: MIT License
Classifier: Programming Language :: Python :: 3
Classifier: Programming Language :: Python :: 3.8
License-File: LICENSE
Requires-Dist: wheel
Requires-Dist: pyaudio
Requires-Dist: numpy
